sarkun/__init__.py
sarkun/sarkun.py
sarkun-0.1.3.dist-info/LICENCE
sarkun-0.1.3.dist-info/METADATA
sarkun-0.1.3.dist-info/WHEEL
sarkun-0.1.3.dist-info/entry_points.txt
sarkun-0.1.3.dist-info/top_level.txt
sarkun-0.1.3.dist-info/RECORD
