Metadata-Version: 2.1
Name: sarkun
Version: 0.1.3
Home-page: https://github.com/kaankarakoc42/sarkun
Author: Mevlüt Kaan Karakoç
Author-email: karakockaan326@gmail.com
License: MIT
Classifier: Programming Language :: Python :: 3
Classifier: License :: OSI Approved :: MIT License
Classifier: Operating System :: OS Independent
License-File: LICENCE
Requires-Dist: pyfiglet
Requires-Dist: colorama
Requires-Dist: emoji
